[
  {
    "title": "中道改革連合　惨敗の原因について語る「若い世代が期日前投票に来てると聞いて嫌な予感がした…これはマズいなと」",
    "url": "https://hamusoku.com/archives/10970938.html",
    "blog_title": "ハムスター速報",
    "date": "2026-02-23 09:35",
    "timestamp": 1771839315.0
  },
  {
    "title": "【Ｘ】高市首相や日本を批判するアカウント群３０００件規模、投稿・拡散…衆院選前から中国系の影響工作か",
    "url": "https://itainews.com/archives/2059192.html",
    "blog_title": "痛いニュース(ﾉ∀`)",
    "date": "2026-02-23 09:30",
    "timestamp": 1771839023.0
  },
  {
    "title": "【画像】東京新聞、捏造の度が過ぎておもちゃにされてしまうｗｗｗ",
    "url": "http://blog.livedoor.jp/kinisoku/archives/5661150.html",
    "blog_title": "キニ速",
    "date": "2026-02-23 09:30",
    "timestamp": 1771839013.0
  },
  {
    "title": "一番稼いだ漫画家って1位は遊戯王の人で2位は原哲夫でええよな？🥺",
    "url": "http://blog.livedoor.jp/goldennews/archives/52299080.html",
    "blog_title": "ゴールデンタイムズ",
    "date": "2026-02-23 09:12",
    "timestamp": 1771837961.0
  },
  {
    "title": "テイルズ←こいつがDQやFFになれなかった理由",
    "url": "http://blog.livedoor.jp/news23vip/archives/6232848.html",
    "blog_title": "VIPPERな俺",
    "date": "2026-02-23 09:08",
    "timestamp": 1771837724.0
  },
  {
    "title": "米(5kg4000円)卵(10個300円)←日本人さん「これ永遠に下がらないヤツだ」と絶望し始める",
    "url": "http://blog.livedoor.jp/kinisoku/archives/5661152.html",
    "blog_title": "キニ速",
    "date": "2026-02-23 09:02",
    "timestamp": 1771837340.0
  },
  {
    "title": "【遊技】「最近のパチンコ荒すぎて打てない」　依存症すら敬遠する“LT機”のムリゲーっぷりを嘆く声",
    "url": "https://itainews.com/archives/2059189.html",
    "blog_title": "痛いニュース(ﾉ∀`)",
    "date": "2026-02-23 09:02",
    "timestamp": 1771837335.0
  },
  {
    "title": "【朗報】愛国者・ゆたぼん(17)、政治家になるという目標を持つｗｗｗｗｗ",
    "url": "https://alfalfalfa.com/articles/11012599.html",
    "blog_title": "アルファルファモザイク＠ネットニュースのまとめ",
    "date": "2026-02-23 09:00",
    "timestamp": 1771837227.0
  },
  {
    "title": "「しつけのためだった」静岡・三島市内の山中に子供を連れて行き置き去りにした男を逮捕",
    "url": "http://blog.livedoor.jp/goldennews/archives/52299079.html",
    "blog_title": "ゴールデンタイムズ",
    "date": "2026-02-23 08:39",
    "timestamp": 1771835982.0
  },
  {
    "title": "【千葉】コンビニでコーヒー万引容疑の匝瑳市副議長、議員辞職　議長「しかるべき判断」",
    "url": "https://itainews.com/archives/2059187.html",
    "blog_title": "痛いニュース(ﾉ∀`)",
    "date": "2026-02-23 08:30",
    "timestamp": 1771835400.0
  },
  {
    "title": "【画像】アニメ史上最高に燃えた炎上、これに決まるｗｗｗｗｗ",
    "url": "http://blog.livedoor.jp/kinisoku/archives/5661149.html",
    "blog_title": "キニ速",
    "date": "2026-02-23 08:21",
    "timestamp": 1771834884.0
  },
  {
    "title": "【悲報】コンサル、株価暴落ｗｗｗｗｗｗｗｗ",
    "url": "https://alfalfalfa.com/articles/11012585.html",
    "blog_title": "アルファルファモザイク＠ネットニュースのまとめ",
    "date": "2026-02-23 08:21",
    "timestamp": 1771834876.0
  },
  {
    "title": "ウクライナ避難民　日本の生活保護受給して定住希望へ",
    "url": "https://hamusoku.com/archives/10970898.html",
    "blog_title": "ハムスター速報",
    "date": "2026-02-23 08:02",
    "timestamp": 1771833726.0
  },
  {
    "title": "中革連・小川淳也代表「エ、エクスタイン文書？…エフスタイン文書？なんですかそれ？」",
    "url": "https://itainews.com/archives/2059185.html",
    "blog_title": "痛いニュース(ﾉ∀`)",
    "date": "2026-02-23 08:01",
    "timestamp": 1771833694.0
  },
  {
    "title": "今考えるとスーパーゲームボーイってすごくないか？",
    "url": "http://blog.livedoor.jp/goldennews/archives/52298243.html",
    "blog_title": "ゴールデンタイムズ",
    "date": "2026-02-23 07:50",
    "timestamp": 1771833039.0
  },
  {
    "title": "【超朗報】女子枠女「女子枠のバッシングのせいで萎縮しちゃう……」→女子枠利用者減",
    "url": "http://blog.livedoor.jp/news23vip/archives/6232838.html",
    "blog_title": "VIPPERな俺",
    "date": "2026-02-23 07:48",
    "timestamp": 1771832930.0
  },
  {
    "title": "2月22日22時22分22:22:22.222を取るスレｗｗｗｗｗｗｗｗｗ",
    "url": "http://blog.livedoor.jp/kinisoku/archives/5661142.html",
    "blog_title": "キニ速",
    "date": "2026-02-23 07:40",
    "timestamp": 1771832412.0
  },
  {
    "title": "King Gnu井口理、ライブ中の客の熱唱を肯定　←　ファン「ずっと歌われるの地獄」「アーティストが認めているなら」賛否の声",
    "url": "https://alfalfalfa.com/articles/11012560.html",
    "blog_title": "アルファルファモザイク＠ネットニュースのまとめ",
    "date": "2026-02-23 07:31",
    "timestamp": 1771831897.0
  },
  {
    "title": "【訃報】LUNA SEAのドラマーの真矢さん死去　56歳",
    "url": "https://itainews.com/archives/2059183.html",
    "blog_title": "痛いニュース(ﾉ∀`)",
    "date": "2026-02-23 07:30",
    "timestamp": 1771831818.0
  },
  {
    "title": "【画像】楽天社員「ちづる」さん、かわいいｗｗｗｗｗｗ【Pickup】",
    "url": "https://alfalfalfa.com/articles/11012447.html",
    "blog_title": "アルファルファモザイク＠ネットニュースのまとめ",
    "date": "2026-02-23 07:21",
    "timestamp": 1771831311.0
  },
  {
    "title": "ビルゲイツ、エプスタイン事件で逃亡",
    "url": "http://blog.livedoor.jp/news23vip/archives/6232834.html",
    "blog_title": "VIPPERな俺",
    "date": "2026-02-23 07:09",
    "timestamp": 1771830572.0
  },
  {
    "title": "【悲報】メキシコ最強カルテルvsメキシコ軍、ガチの全面戦争へ。街が『CoD』のステージ化して無事死亡",
    "url": "http://blog.livedoor.jp/kinisoku/archives/5661135.html",
    "blog_title": "キニ速",
    "date": "2026-02-23 07:00",
    "timestamp": 1771830059.0
  },
  {
    "title": "【風呂キャンセル界隈】素人はSNSをやるなと言っていたチョコレートプラネットさん　素人のネタをパクッて今日も荒稼ぎ",
    "url": "https://hamusoku.com/archives/10970894.html",
    "blog_title": "ハムスター速報",
    "date": "2026-02-23 06:34",
    "timestamp": 1771828493.0
  },
  {
    "title": "【悲報】奨学金金利、爆上げでヤバいことに",
    "url": "https://alfalfalfa.com/articles/11012542.html",
    "blog_title": "アルファルファモザイク＠ネットニュースのまとめ",
    "date": "2026-02-23 06:30",
    "timestamp": 1771828219.0
  },
  {
    "title": "ビルゲイツ、エプスタイン事件で逃亡",
    "url": "https://nwknews.jp/archives/6232828.html",
    "blog_title": "哲学ニュースnwk",
    "date": "2026-02-23 06:19",
    "timestamp": 1771827595.0
  },
  {
    "title": "ドコモ・au・ソフバン「スマホ返却の際に特典利用料を徴収します😁」",
    "url": "http://blog.livedoor.jp/goldennews/archives/52299072.html",
    "blog_title": "ゴールデンタイムズ",
    "date": "2026-02-23 06:16",
    "timestamp": 1771827371.0
  },
  {
    "title": "スカイツリーでエレベーター停止　20人が閉じ込められ約6時間後に救助",
    "url": "http://blog.livedoor.jp/goldennews/archives/52299068.html",
    "blog_title": "ゴールデンタイムズ",
    "date": "2026-02-23 05:41",
    "timestamp": 1771825309.0
  },
  {
    "title": "生活保護受給者がスイッチ２を購入　納税者にメッセージ",
    "url": "https://hamusoku.com/archives/10970887.html",
    "blog_title": "ハムスター速報",
    "date": "2026-02-23 05:09",
    "timestamp": 1771823351.0
  },
  {
    "title": "大津市｢保育士の給料が低くて不満が出てる…？せや！｣",
    "url": "http://blog.livedoor.jp/news23vip/archives/6232819.html",
    "blog_title": "VIPPERな俺",
    "date": "2026-02-23 04:52",
    "timestamp": 1771822347.0
  },
  {
    "title": "とある精神科のクチコミ　ヤバすぎると話題に",
    "url": "https://hamusoku.com/archives/10970872.html",
    "blog_title": "ハムスター速報",
    "date": "2026-02-23 03:47",
    "timestamp": 1771818425.0
  },
  {
    "title": "「King Gnuのライブで歌うのがイヤってヤツには注意させていただきます」",
    "url": "http://blog.livedoor.jp/news23vip/archives/6232814.html",
    "blog_title": "VIPPERな俺",
    "date": "2026-02-23 03:34",
    "timestamp": 1771817659.0
  },
  {
    "title": "総合商社（三菱商事とか三井物産）の社員って化け物レベルにタフらしいけど実際どんくらいなん？",
    "url": "https://nwknews.jp/archives/6232807.html",
    "blog_title": "哲学ニュースnwk",
    "date": "2026-02-23 03:00",
    "timestamp": 1771815628.0
  },
  {
    "title": "【緊張拡大】メキシコ、カルテルと軍の衝突激化…現地かなりヤバい模様",
    "url": "https://nwknews.jp/archives/6232792.html",
    "blog_title": "哲学ニュースnwk",
    "date": "2026-02-23 01:00",
    "timestamp": 1771808453.0
  },
  {
    "title": "【訃報】LUNA SEA真矢さん死去（56）←マジで信じられないんだが…",
    "url": "https://nwknews.jp/archives/6232790.html",
    "blog_title": "哲学ニュースnwk",
    "date": "2026-02-22 23:21",
    "timestamp": 1771802499.0
  },
  {
    "title": "外国人「帰る時間に厳しくないのに出社だけ厳しい日本企業って何？」",
    "url": "https://nwknews.jp/archives/6232786.html",
    "blog_title": "哲学ニュースnwk",
    "date": "2026-02-22 22:35",
    "timestamp": 1771799714.0
  }
]