[
  {
    "title": "【悲報】マクドナルドさん、古の2chネタを公式に採用してしまう…",
    "url": "https://alfalfalfa.com/articles/10986842.html",
    "blog_title": "アルファルファモザイク＠ネットニュースのまとめ",
    "date": "2026-01-08 05:00",
    "timestamp": 1767848406.0
  },
  {
    "title": "【悲報】中国、日本人の命も握っていた…  抗生物質原料１００％中国産wwwwwwwwwwwww",
    "url": "https://alfalfalfa.com/articles/10986841.html",
    "blog_title": "アルファルファモザイク＠ネットニュースのまとめ",
    "date": "2026-01-08 04:32",
    "timestamp": 1767846772.0
  },
  {
    "title": "【大阪】元男性が女湯入浴「手の届く距離に女の子」レビューが物議、施設は確認取れず 厚労省が明かした基準",
    "url": "https://itainews.com/archives/2057333.html",
    "blog_title": "痛いニュース(ﾉ∀`)",
    "date": "2026-01-08 04:31",
    "timestamp": 1767846672.0
  },
  {
    "title": "尾田栄一郎が後悔してそうな設定",
    "url": "http://blog.livedoor.jp/news23vip/archives/6227570.html",
    "blog_title": "VIPPERな俺",
    "date": "2026-01-08 04:30",
    "timestamp": 1767846628.0
  },
  {
    "title": "【悲報】山里亮太「罪滅ぼしのためにフィリピンに子ども食堂を作ったってネットで言われてる」",
    "url": "http://blog.livedoor.jp/kinisoku/archives/5651549.html",
    "blog_title": "キニ速",
    "date": "2026-01-08 04:20",
    "timestamp": 1767846009.0
  },
  {
    "title": "スマイリーキクチ、栃木高校イジメ動画に「被害者は加害者がネットリンチに遭って喜ぶと思いますか？」",
    "url": "https://itainews.com/archives/2057342.html",
    "blog_title": "痛いニュース(ﾉ∀`)",
    "date": "2026-01-08 04:02",
    "timestamp": 1767844949.0
  },
  {
    "title": "【画像】白人「これが日本の伝統衣装なのね！着てみるわ！」　→結果",
    "url": "https://alfalfalfa.com/articles/10986804.html",
    "blog_title": "アルファルファモザイク＠ネットニュースのまとめ",
    "date": "2026-01-08 04:01",
    "timestamp": 1767844888.0
  },
  {
    "title": "【悲報】ミナデインを使うメリット、無い",
    "url": "http://blog.livedoor.jp/goldennews/archives/52297019.html",
    "blog_title": "ゴールデンタイムズ",
    "date": "2026-01-08 04:00",
    "timestamp": 1767844834.0
  },
  {
    "title": "元カノに復讐したい 元カノが一番嫌がること教えてくれ",
    "url": "http://blog.livedoor.jp/kinisoku/archives/5649392.html",
    "blog_title": "キニ速",
    "date": "2026-01-08 03:40",
    "timestamp": 1767843628.0
  },
  {
    "title": "頂き女子りりちゃん「反省…こんなわたしのことは忘れてね」　満期出所まであと7年3ヶ月　2025.12.23",
    "url": "https://itainews.com/archives/2057332.html",
    "blog_title": "痛いニュース(ﾉ∀`)",
    "date": "2026-01-08 03:31",
    "timestamp": 1767843075.0
  },
  {
    "title": "結婚諦めたワイ(24)の休日",
    "url": "https://hamusoku.com/archives/10949806.html",
    "blog_title": "ハムスター速報",
    "date": "2026-01-08 03:30",
    "timestamp": 1767843055.0
  },
  {
    "title": "【画像】41歳の美人vs26歳の美人がまあまあいい勝負でワロスｗｗｗｗｗｗｗｗｗｗｗｗｗｗ",
    "url": "https://alfalfalfa.com/articles/10986805.html",
    "blog_title": "アルファルファモザイク＠ネットニュースのまとめ",
    "date": "2026-01-08 03:30",
    "timestamp": 1767843002.0
  },
  {
    "title": "日本人「家建てたろ！窓はアルミサッシでええか」→海外「ｗｗｗ」",
    "url": "https://nwknews.jp/archives/6227586.html",
    "blog_title": "哲学ニュースnwk",
    "date": "2026-01-08 03:28",
    "timestamp": 1767842912.0
  },
  {
    "title": "【画像】美女さん、彼氏に電卓を晒され咽び泣く…",
    "url": "http://blog.livedoor.jp/kinisoku/archives/5651543.html",
    "blog_title": "キニ速",
    "date": "2026-01-08 03:22",
    "timestamp": 1767842569.0
  },
  {
    "title": "家系ラーメンって「全部ふつう」が店側の理想の味なんだよな？",
    "url": "http://blog.livedoor.jp/goldennews/archives/52297095.html",
    "blog_title": "ゴールデンタイムズ",
    "date": "2026-01-08 03:12",
    "timestamp": 1767841975.0
  },
  {
    "title": "【画像】小向美奈子さん、めちゃくちゃ痩せてしまう・・・・・",
    "url": "http://blog.livedoor.jp/kinisoku/archives/5649916.html",
    "blog_title": "キニ速",
    "date": "2026-01-08 03:06",
    "timestamp": 1767841604.0
  },
  {
    "title": "【速報】X-MENはアベンジャーズ：ドゥームズデイで帰ってくる、第三弾予告が公開へ",
    "url": "https://alfalfalfa.com/articles/10986803.html",
    "blog_title": "アルファルファモザイク＠ネットニュースのまとめ",
    "date": "2026-01-08 03:01",
    "timestamp": 1767841301.0
  },
  {
    "title": "【悲報】パパ活女さんカンボジアに行って薬漬け&骨折で帰国ww",
    "url": "http://blog.livedoor.jp/news23vip/archives/6227569.html",
    "blog_title": "VIPPERな俺",
    "date": "2026-01-08 03:00",
    "timestamp": 1767841246.0
  },
  {
    "title": "【文春】米倉涼子「麻薬疑惑」で逮捕状が請求されていた！",
    "url": "https://itainews.com/archives/2057324.html",
    "blog_title": "痛いニュース(ﾉ∀`)",
    "date": "2026-01-08 03:00",
    "timestamp": 1767841225.0
  },
  {
    "title": "渡邊渚「防犯上リアルタイム投稿しない派」「写真が時系列通りに並ぶことない」一部臆測に言及か",
    "url": "https://itainews.com/archives/2057330.html",
    "blog_title": "痛いニュース(ﾉ∀`)",
    "date": "2026-01-08 02:31",
    "timestamp": 1767839477.0
  },
  {
    "title": "【速報】トランプ、66の国際機関からアメリカ脱退署名ｗｗｗｗｗ",
    "url": "https://nwknews.jp/archives/6227579.html",
    "blog_title": "哲学ニュースnwk",
    "date": "2026-01-08 02:27",
    "timestamp": 1767839222.0
  },
  {
    "title": "粗品「粗品おもんないって言ってるアンチ共、お前らは2400万円寄付できんの？」",
    "url": "http://blog.livedoor.jp/kinisoku/archives/5650884.html",
    "blog_title": "キニ速",
    "date": "2026-01-08 02:20",
    "timestamp": 1767838827.0
  },
  {
    "title": "【悲報】ボディバッグを愛用していた男性、ネットの風評に気づいてしまう",
    "url": "http://blog.livedoor.jp/goldennews/archives/52297099.html",
    "blog_title": "ゴールデンタイムズ",
    "date": "2026-01-08 02:12",
    "timestamp": 1767838340.0
  },
  {
    "title": "【悲報】第三次世界大戦、開始",
    "url": "http://blog.livedoor.jp/news23vip/archives/6227566.html",
    "blog_title": "VIPPERな俺",
    "date": "2026-01-08 01:45",
    "timestamp": 1767836703.0
  },
  {
    "title": "さいたまスーパーアリーナ、老朽化に伴う大規模改修で休館へ　今月13日から最長1年半",
    "url": "http://blog.livedoor.jp/goldennews/archives/52297105.html",
    "blog_title": "ゴールデンタイムズ",
    "date": "2026-01-08 01:12",
    "timestamp": 1767834729.0
  },
  {
    "title": "【悲報】 ベネズエラの石油売却利益、トランプが管理　米国とかじゃなくトランプ個人が管理",
    "url": "http://blog.livedoor.jp/goldennews/archives/52297136.html",
    "blog_title": "ゴールデンタイムズ",
    "date": "2026-01-08 00:39",
    "timestamp": 1767832798.0
  },
  {
    "title": "資生堂、257人退職へ",
    "url": "http://blog.livedoor.jp/news23vip/archives/6227565.html",
    "blog_title": "VIPPERな俺",
    "date": "2026-01-08 00:30",
    "timestamp": 1767832250.0
  },
  {
    "title": "友達の漫画家志望「あのぅ、自分絵柄が古くてぇ……w」ワイ「………はっきり言いますね。」",
    "url": "https://hamusoku.com/archives/10949782.html",
    "blog_title": "ハムスター速報",
    "date": "2026-01-08 00:08",
    "timestamp": 1767830901.0
  },
  {
    "title": "菅直人元首相、要介護3・認知症に　東日本大震災の記憶は「覚えていない」",
    "url": "https://nwknews.jp/archives/6227564.html",
    "blog_title": "哲学ニュースnwk",
    "date": "2026-01-07 23:51",
    "timestamp": 1767829885.0
  },
  {
    "title": "担任「えー、俺君がカレーの鍋をひっくり返したので今日はカレー無しです。」小学生俺「あ…あ……！」",
    "url": "http://blog.livedoor.jp/news23vip/archives/6227563.html",
    "blog_title": "VIPPERな俺",
    "date": "2026-01-07 23:46",
    "timestamp": 1767829563.0
  },
  {
    "title": "黒板をノートに書き写す作業、正直一番ムダじゃね？",
    "url": "https://nwknews.jp/archives/6227562.html",
    "blog_title": "哲学ニュースnwk",
    "date": "2026-01-07 23:19",
    "timestamp": 1767827940.0
  },
  {
    "title": "早期内定貰ったところが月平均残業６０時間越えてるんだが",
    "url": "https://hamusoku.com/archives/10948183.html",
    "blog_title": "ハムスター速報",
    "date": "2026-01-07 22:06",
    "timestamp": 1767823571.0
  },
  {
    "title": "【画像】何回見ても笑ってしまう画像貼っていけｗｗｗ",
    "url": "https://nwknews.jp/archives/6227553.html",
    "blog_title": "哲学ニュースnwk",
    "date": "2026-01-07 17:50",
    "timestamp": 1767808202.0
  },
  {
    "title": "紀州みなべ梅干協同組合「中国産の梅を使っていきます！」→紀州梅農家「外国産にシフトしたら国産梅の需要は戻りません。傷のある梅を使った国産梅肉チューブを広めてください」",
    "url": "https://hamusoku.com/archives/10957049.html",
    "blog_title": "ハムスター速報",
    "date": "2026-01-07 12:41",
    "timestamp": 1767789671.0
  },
  {
    "title": "ホロライブさくらみこさん　お気持ち表明",
    "url": "https://hamusoku.com/archives/10957229.html",
    "blog_title": "ハムスター速報",
    "date": "2026-01-07 09:41",
    "timestamp": 1767778872.0
  }
]