[
  {
    "title": "【名言】諭吉「天は人の上に人を作らず」俺「じゃあ今の格差社会おかしい！」諭吉「…これには続きがある」",
    "url": "https://nwknews.jp/archives/6235802.html",
    "blog_title": "哲学ニュースnwk",
    "date": "2026-03-19 15:31",
    "timestamp": 1773934311.0
  },
  {
    "title": "【画像】瑠璃の宝石の荒砥凪さんガタイが良くてエロすぎるｗｗｗｗｗ",
    "url": "http://blog.livedoor.jp/kinisoku/archives/5666371.html",
    "blog_title": "キニ速",
    "date": "2026-03-19 15:30",
    "timestamp": 1773934228.0
  },
  {
    "title": "【悲報】辺野古新基地反対運動、どんどんヤベー情報が掘られていく【Pickup】",
    "url": "https://alfalfalfa.com/articles/11020786.html",
    "blog_title": "アルファルファモザイク＠ネットニュースのまとめ",
    "date": "2026-03-19 15:30",
    "timestamp": 1773934219.0
  },
  {
    "title": "【ホロライブ】宝鐘マリン、結婚の条件がこちらｗｗｗｗｗｗｗｗｗｗｗｗｗｗｗｗｗｗｗｗｗｗｗｗｗｗｗｗｗｗｗｗｗｗｗ【PickupYoutube】",
    "url": "https://alfalfalfa.com/articles/11020782.html",
    "blog_title": "アルファルファモザイク＠ネットニュースのまとめ",
    "date": "2026-03-19 15:20",
    "timestamp": 1773933657.0
  },
  {
    "title": "高市「大統領、会えて光栄です」トランプ「おう！さっそくだけどワーキングランチ中止な！」",
    "url": "http://blog.livedoor.jp/goldennews/archives/52300171.html",
    "blog_title": "ゴールデンタイムズ",
    "date": "2026-03-19 15:18",
    "timestamp": 1773933480.0
  },
  {
    "title": "同志社国際高校と活動家団体の主張、矛盾しまくってしまう…",
    "url": "http://blog.livedoor.jp/goldennews/archives/52300170.html",
    "blog_title": "ゴールデンタイムズ",
    "date": "2026-03-19 15:07",
    "timestamp": 1773932821.0
  },
  {
    "title": "熊田曜子（43）唐突に激エロ大胆手ブラショットを公開してしまうｗｗｗｗ",
    "url": "http://blog.livedoor.jp/kinisoku/archives/5666422.html",
    "blog_title": "キニ速",
    "date": "2026-03-19 15:00",
    "timestamp": 1773932429.0
  },
  {
    "title": "トラック特攻名所と化していた高架下、住民の陳情により高さ制限看板が設置される →",
    "url": "http://blog.livedoor.jp/goldennews/archives/52300155.html",
    "blog_title": "ゴールデンタイムズ",
    "date": "2026-03-19 14:58",
    "timestamp": 1773932280.0
  },
  {
    "title": "学生「金ないンゴ…」Apple「iPhoneの価値は電話単体の価値を超えている」",
    "url": "http://blog.livedoor.jp/news23vip/archives/6235799.html",
    "blog_title": "VIPPERな俺",
    "date": "2026-03-19 14:52",
    "timestamp": 1773931935.0
  },
  {
    "title": "【悲報】女さん、友達に整形を暴露されてブチギレ",
    "url": "https://alfalfalfa.com/articles/11020853.html",
    "blog_title": "アルファルファモザイク＠ネットニュースのまとめ",
    "date": "2026-03-19 14:46",
    "timestamp": 1773931599.0
  },
  {
    "title": "【悪夢の民主党の置き土産】高市政権　メガソーラー支援廃止を正式決定　民主党のせいで再エネ賦課金の世帯負担は初の年額2万円台",
    "url": "https://hamusoku.com/archives/10977831.html",
    "blog_title": "ハムスター速報",
    "date": "2026-03-19 14:42",
    "timestamp": 1773931361.0
  },
  {
    "title": "美人声優さん、スタメンポケモンを並べただけで炎上し謝罪ｗｗｗｗｗ",
    "url": "http://blog.livedoor.jp/kinisoku/archives/5666327.html",
    "blog_title": "キニ速",
    "date": "2026-03-19 14:30",
    "timestamp": 1773930617.0
  },
  {
    "title": "海外ドラマ専門チャンネル「スーパー！ドラマTV 　6月末での閉局を発表　37年の歴史に幕",
    "url": "https://itainews.com/archives/2060191.html",
    "blog_title": "痛いニュース(ﾉ∀`)",
    "date": "2026-03-19 14:01",
    "timestamp": 1773928894.0
  },
  {
    "title": "ブス巨乳ってなんでエロいの？",
    "url": "http://blog.livedoor.jp/kinisoku/archives/5666519.html",
    "blog_title": "キニ速",
    "date": "2026-03-19 14:00",
    "timestamp": 1773928823.0
  },
  {
    "title": "クマ、冬眠明けでまた活動が活発に　北海道猟友会のトップ「クマ駆除から外してもらいたい」",
    "url": "http://blog.livedoor.jp/goldennews/archives/52300162.html",
    "blog_title": "ゴールデンタイムズ",
    "date": "2026-03-19 14:00",
    "timestamp": 1773928800.0
  },
  {
    "title": "【悲報】高市とトランプのワーキングランチ中止…水面下で何が起こっているのか",
    "url": "https://alfalfalfa.com/articles/11020833.html",
    "blog_title": "アルファルファモザイク＠ネットニュースのまとめ",
    "date": "2026-03-19 13:59",
    "timestamp": 1773928758.0
  },
  {
    "title": "【悲報】メガソーラー支援廃止へｗｗｗｗｗ　2027年度以降は新規対象外に",
    "url": "https://nwknews.jp/archives/6235792.html",
    "blog_title": "哲学ニュースnwk",
    "date": "2026-03-19 13:55",
    "timestamp": 1773928550.0
  },
  {
    "title": "コードギアスの扇、声優さんから誕生日を祝われる",
    "url": "http://blog.livedoor.jp/goldennews/archives/52300154.html",
    "blog_title": "ゴールデンタイムズ",
    "date": "2026-03-19 13:50",
    "timestamp": 1773928200.0
  },
  {
    "title": "朝起きたら 俺の “イモウト” が “ポテト” になっていたｗｗｗｗｗｗｗｗｗｗｗｗｗｗｗ",
    "url": "https://hamusoku.com/archives/10977755.html",
    "blog_title": "ハムスター速報",
    "date": "2026-03-19 13:36",
    "timestamp": 1773927374.0
  },
  {
    "title": "【画像】女さん「婚活市場の普通の男がこれです」←女性が可哀想だと話題に・・・",
    "url": "http://blog.livedoor.jp/kinisoku/archives/5666319.html",
    "blog_title": "キニ速",
    "date": "2026-03-19 13:30",
    "timestamp": 1773927026.0
  },
  {
    "title": "インフルエンサー・宮崎麗果さん、約1.5億円の脱税認める",
    "url": "https://alfalfalfa.com/articles/11020825.html",
    "blog_title": "アルファルファモザイク＠ネットニュースのまとめ",
    "date": "2026-03-19 13:24",
    "timestamp": 1773926686.0
  },
  {
    "title": "ハイキューってほんまに腐女子アニメなん？",
    "url": "http://blog.livedoor.jp/news23vip/archives/6235782.html",
    "blog_title": "VIPPERな俺",
    "date": "2026-03-19 13:05",
    "timestamp": 1773925510.0
  },
  {
    "title": "【悲報】フジテレビさん、4月からとんでもないドラマを放映する模様ｗｗｗｗｗｗｗｗｗｗｗｗｗｗｗ",
    "url": "https://itainews.com/archives/2060181.html",
    "blog_title": "痛いニュース(ﾉ∀`)",
    "date": "2026-03-19 13:04",
    "timestamp": 1773925473.0
  },
  {
    "title": "【悲報】イラン戦争、もうめっちゃくちゃ",
    "url": "https://nwknews.jp/archives/6235781.html",
    "blog_title": "哲学ニュースnwk",
    "date": "2026-03-19 12:48",
    "timestamp": 1773924499.0
  },
  {
    "title": "ピッチクロック採用見送り、飲食やグッズ販売で球場に観客が長く滞在することを望む球団が固辞…打者と投手の「間」を大切にする文化",
    "url": "https://itainews.com/archives/2060180.html",
    "blog_title": "痛いニュース(ﾉ∀`)",
    "date": "2026-03-19 12:02",
    "timestamp": 1773921764.0
  },
  {
    "title": "【悲報】韓国の超大作オープンワールドゲーム「紅の砂漠」メタスコア78点で大不評wwwwwwwwwwww",
    "url": "https://nwknews.jp/archives/6235775.html",
    "blog_title": "哲学ニュースnwk",
    "date": "2026-03-19 11:37",
    "timestamp": 1773920245.0
  },
  {
    "title": "れいわ大石「日曜討論に出たから見て見て」→著作権侵害でアカウント凍結され発狂",
    "url": "https://itainews.com/archives/2060190.html",
    "blog_title": "痛いニュース(ﾉ∀`)",
    "date": "2026-03-19 11:31",
    "timestamp": 1773919871.0
  },
  {
    "title": "最近の彼岸島　ひどすぎるｗｗｗｗｗｗｗｗｗｗｗｗｗｗｗ",
    "url": "https://hamusoku.com/archives/10977786.html",
    "blog_title": "ハムスター速報",
    "date": "2026-03-19 11:03",
    "timestamp": 1773918191.0
  },
  {
    "title": "フランス軍、レバノン支援表明、イスラエルのナチスによる虐殺を止めると宣言😲",
    "url": "https://itainews.com/archives/2060178.html",
    "blog_title": "痛いニュース(ﾉ∀`)",
    "date": "2026-03-19 11:02",
    "timestamp": 1773918129.0
  },
  {
    "title": "【悲報】自転車さん、2週間後にガチのマジの地獄へ",
    "url": "http://blog.livedoor.jp/news23vip/archives/6235756.html",
    "blog_title": "VIPPERな俺",
    "date": "2026-03-19 10:30",
    "timestamp": 1773916246.0
  },
  {
    "title": "３２歳無職　父親に殺される",
    "url": "https://hamusoku.com/archives/10977722.html",
    "blog_title": "ハムスター速報",
    "date": "2026-03-19 09:43",
    "timestamp": 1773913380.0
  },
  {
    "title": "【画】ドラッグストアの弁当が限界突破wwwwwwwww",
    "url": "https://nwknews.jp/archives/6235763.html",
    "blog_title": "哲学ニュースnwk",
    "date": "2026-03-19 09:05",
    "timestamp": 1773911149.0
  },
  {
    "title": "トランプが日本にしてくれたこと一覧",
    "url": "http://blog.livedoor.jp/news23vip/archives/6235749.html",
    "blog_title": "VIPPERな俺",
    "date": "2026-03-19 09:00",
    "timestamp": 1773910801.0
  },
  {
    "title": "【中国決済アプリ】Alipay・WeChat Payでの決済が広がりすぎて脱税やり放題だと話題に",
    "url": "https://hamusoku.com/archives/10977218.html",
    "blog_title": "ハムスター速報",
    "date": "2026-03-19 07:53",
    "timestamp": 1773906795.0
  },
  {
    "title": "在宅勤務とかいう神みたいな働き方",
    "url": "http://blog.livedoor.jp/news23vip/archives/6235754.html",
    "blog_title": "VIPPERな俺",
    "date": "2026-03-19 07:44",
    "timestamp": 1773906246.0
  }
]