[
  {
    "title": "【サッカー】セネガル代表チームドクター、専門が産婦人科だったと発覚し契約終了へ",
    "url": "https://alfalfalfa.com/articles/11087830.html",
    "blog_title": "アルファルファモザイク＠ネットニュースのまとめ",
    "date": "2026-07-15 18:00",
    "timestamp": 1784138447.0
  },
  {
    "title": "もうスパロボは終わりや",
    "url": "http://blog.livedoor.jp/news23vip/archives/6249584.html",
    "blog_title": "VIPPERな俺",
    "date": "2026-07-15 18:00",
    "timestamp": 1784138427.0
  },
  {
    "title": "PS5エミュレーター、着々と開発が進んでいたｗｗｗｗｗ",
    "url": "http://blog.livedoor.jp/kinisoku/archives/5692359.html",
    "blog_title": "キニ速",
    "date": "2026-07-15 18:00",
    "timestamp": 1784138406.0
  },
  {
    "title": "【画像】美人すぎる元甲子園ビールの売り子、レベチｗｗｗｗｗｗｗｗｗｗｗｗｗｗｗｗｗｗｗｗｗｗｗｗｗｗｗｗｗｗ 【Pickup15072403】",
    "url": "https://alfalfalfa.com/articles/11087767.html",
    "blog_title": "アルファルファモザイク＠ネットニュースのまとめ",
    "date": "2026-07-15 17:50",
    "timestamp": 1784137843.0
  },
  {
    "title": "ゲーマー「伝説のパルだ！」ｷｬｯｷｬ 　？？「...それカイオーガだよ」→何故か叩かれるｗｗｗｗｗ",
    "url": "http://blog.livedoor.jp/kinisoku/archives/5692397.html",
    "blog_title": "キニ速",
    "date": "2026-07-15 17:00",
    "timestamp": 1784134858.0
  },
  {
    "title": "【絶望】2025年1月ハワイ豪遊で1846万円の税金を溶かした4人がこちら",
    "url": "https://alfalfalfa.com/articles/11087827.html",
    "blog_title": "アルファルファモザイク＠ネットニュースのまとめ",
    "date": "2026-07-15 17:00",
    "timestamp": 1784134816.0
  },
  {
    "title": "【画像】男子をガン詰めするJKの目、レベチｗｗｗｗｗｗｗｗｗｗｗｗｗｗｗｗｗ 【Pickup15072406】",
    "url": "https://alfalfalfa.com/articles/11087768.html",
    "blog_title": "アルファルファモザイク＠ネットニュースのまとめ",
    "date": "2026-07-15 16:50",
    "timestamp": 1784134220.0
  },
  {
    "title": "【画像】お前らが腹筋崩壊するほど笑った画像、貼っていけｗｗｗｗｗｗｗ",
    "url": "https://nwknews.jp/archives/6249573.html",
    "blog_title": "哲学ニュースnwk",
    "date": "2026-07-15 16:00",
    "timestamp": 1784131255.0
  },
  {
    "title": "【大荒れ】新弾BOX購入権をめぐりカードショップに批判集まる「抱き合わせでは？」",
    "url": "https://alfalfalfa.com/articles/11087870.html",
    "blog_title": "アルファルファモザイク＠ネットニュースのまとめ",
    "date": "2026-07-15 16:00",
    "timestamp": 1784131245.0
  },
  {
    "title": "【悲報】米津玄師、イキりだす「俺はニコニコ動画というインターネットの無法地帯で育った男ですよ？(笑)」",
    "url": "http://blog.livedoor.jp/kinisoku/archives/5692374.html",
    "blog_title": "キニ速",
    "date": "2026-07-15 16:00",
    "timestamp": 1784131231.0
  },
  {
    "title": "もうPS6の話してるってなんかすげーなぁ",
    "url": "http://blog.livedoor.jp/goldennews/archives/52305407.html",
    "blog_title": "ゴールデンタイムズ",
    "date": "2026-07-15 15:39",
    "timestamp": 1784129940.0
  },
  {
    "title": "ジャンプ買い占めにより「ジャンプ卒業」がトレンドになってしまうｗｗｗｗ",
    "url": "http://blog.livedoor.jp/kinisoku/archives/5692404.html",
    "blog_title": "キニ速",
    "date": "2026-07-15 15:30",
    "timestamp": 1784129405.0
  },
  {
    "title": "でも銀だこってうまいよな🥺",
    "url": "http://blog.livedoor.jp/goldennews/archives/52304998.html",
    "blog_title": "ゴールデンタイムズ",
    "date": "2026-07-15 15:12",
    "timestamp": 1784128320.0
  },
  {
    "title": "【謎理論】「辛いことを経験した人ほど精神的に強い」←むしろ壊れる人も多いだろｗｗｗｗｗ",
    "url": "https://nwknews.jp/archives/6249572.html",
    "blog_title": "哲学ニュースnwk",
    "date": "2026-07-15 15:01",
    "timestamp": 1784127695.0
  },
  {
    "title": "【朗報】中国さん、セ●クスできそうな美少女ロボを異常な速度で進化させるｗｗｗｗ",
    "url": "http://blog.livedoor.jp/kinisoku/archives/5692370.html",
    "blog_title": "キニ速",
    "date": "2026-07-15 15:00",
    "timestamp": 1784127621.0
  },
  {
    "title": "【画像】仙台育英、初の女子野球部員が無事ベンチ入り",
    "url": "http://blog.livedoor.jp/news23vip/archives/6249537.html",
    "blog_title": "VIPPERな俺",
    "date": "2026-07-15 15:00",
    "timestamp": 1784127615.0
  },
  {
    "title": "東方不敗マスター・アジアって結構ちゃんと悪党だよね",
    "url": "http://blog.livedoor.jp/goldennews/archives/52305043.html",
    "blog_title": "ゴールデンタイムズ",
    "date": "2026-07-15 14:46",
    "timestamp": 1784126760.0
  },
  {
    "title": "病院で点滴に大便注入疑い、女逮捕",
    "url": "https://itainews.com/archives/2064866.html",
    "blog_title": "痛いニュース(ﾉ∀`)",
    "date": "2026-07-15 14:01",
    "timestamp": 1784124088.0
  },
  {
    "title": "【犯罪心理】ジャン＝クロード・ロマン事件　18年間「WHOの医師」を演じた男は、なぜ家族5人を殺したのか",
    "url": "https://nwknews.jp/archives/6249566.html",
    "blog_title": "哲学ニュースnwk",
    "date": "2026-07-15 14:00",
    "timestamp": 1784124019.0
  },
  {
    "title": "宮崎県警の施設で勾留されていた男性、警察官2人から尻を触るなどのセクハラを受けたとして提訴",
    "url": "http://blog.livedoor.jp/goldennews/archives/52305394.html",
    "blog_title": "ゴールデンタイムズ",
    "date": "2026-07-15 13:50",
    "timestamp": 1784123400.0
  },
  {
    "title": "【朗報】ワキガワイ、空調服をゲット！",
    "url": "https://hamusoku.com/archives/11020593.html",
    "blog_title": "ハムスター速報",
    "date": "2026-07-15 13:48",
    "timestamp": 1784123280.0
  },
  {
    "title": "【悲報】このクソしょぼいトイレ、建設費2億円、移設にさらに1億円かかる",
    "url": "http://blog.livedoor.jp/news23vip/archives/6249526.html",
    "blog_title": "VIPPERな俺",
    "date": "2026-07-15 13:30",
    "timestamp": 1784122210.0
  },
  {
    "title": "ANA機長、女性CAへの不同意わいせつ罪で懲役1年8カ月の実刑判決",
    "url": "http://blog.livedoor.jp/goldennews/archives/52305388.html",
    "blog_title": "ゴールデンタイムズ",
    "date": "2026-07-15 13:28",
    "timestamp": 1784122080.0
  },
  {
    "title": "【滋賀】ボルトが入った計100キロの鉄製のカゴと作業用のローラーに頭を挟まれ　31歳男性が死亡　長浜市の工場",
    "url": "https://itainews.com/archives/2064860.html",
    "blog_title": "痛いニュース(ﾉ∀`)",
    "date": "2026-07-15 13:02",
    "timestamp": 1784120566.0
  },
  {
    "title": "お前らが「長野県」について知ってることを教えてください",
    "url": "https://nwknews.jp/archives/6249555.html",
    "blog_title": "哲学ニュースnwk",
    "date": "2026-07-15 13:00",
    "timestamp": 1784120428.0
  },
  {
    "title": "ヨドバシカメラ池袋線　電車で脱糞してしまう・・・",
    "url": "https://hamusoku.com/archives/11020954.html",
    "blog_title": "ハムスター速報",
    "date": "2026-07-15 12:37",
    "timestamp": 1784119074.0
  },
  {
    "title": "道頓堀ビル火災　書類送検された元飲食店従業員の男　日常的にたばこをポイ捨て　ポイ捨ての約15分後に出火か",
    "url": "https://itainews.com/archives/2064859.html",
    "blog_title": "痛いニュース(ﾉ∀`)",
    "date": "2026-07-15 12:03",
    "timestamp": 1784116992.0
  },
  {
    "title": "【衝撃】道頓堀ビル火災で消防隊員2人死亡…書類送検の35歳男、日常的に火のついたタバコをポイ捨て　約15分後に出火か",
    "url": "https://nwknews.jp/archives/6249533.html",
    "blog_title": "哲学ニュースnwk",
    "date": "2026-07-15 12:00",
    "timestamp": 1784116843.0
  },
  {
    "title": "赤羽vs中野vs北千住",
    "url": "http://blog.livedoor.jp/news23vip/archives/6249535.html",
    "blog_title": "VIPPERな俺",
    "date": "2026-07-15 12:00",
    "timestamp": 1784116803.0
  },
  {
    "title": "【悲報】我が家エアコン無い　がちで死にそう",
    "url": "https://hamusoku.com/archives/11020891.html",
    "blog_title": "ハムスター速報",
    "date": "2026-07-15 11:29",
    "timestamp": 1784114940.0
  },
  {
    "title": "【ルッキズム】なぜ男性の「チビ･デブ･ハゲ」は“いじっていい”ことになるのか…「傷つかないだろう」の思い込みの下で",
    "url": "https://itainews.com/archives/2064857.html",
    "blog_title": "痛いニュース(ﾉ∀`)",
    "date": "2026-07-15 11:02",
    "timestamp": 1784113354.0
  },
  {
    "title": "【山梨】空き家侵入窃盗事件　現金約1万円を盗んだ疑い　逮捕されたベトナム人4人を不起訴処分",
    "url": "https://itainews.com/archives/2064867.html",
    "blog_title": "痛いニュース(ﾉ∀`)",
    "date": "2026-07-15 10:31",
    "timestamp": 1784111515.0
  },
  {
    "title": "【悲報】移民受け入れ、流石にちょっと笑えない",
    "url": "http://blog.livedoor.jp/news23vip/archives/6249538.html",
    "blog_title": "VIPPERな俺",
    "date": "2026-07-15 10:30",
    "timestamp": 1784111430.0
  },
  {
    "title": "【病院脱糞事件】５１歳助産師　点滴に大便を混入させて患者を殺害",
    "url": "https://hamusoku.com/archives/11020961.html",
    "blog_title": "ハムスター速報",
    "date": "2026-07-15 09:41",
    "timestamp": 1784108486.0
  },
  {
    "title": "【オワコン】ひろゆきが必死に宣伝していたPOPOPO　サービス終了ｗｗｗｗｗｗｗｗｗｗｗｗ",
    "url": "https://hamusoku.com/archives/11020942.html",
    "blog_title": "ハムスター速報",
    "date": "2026-07-15 08:50",
    "timestamp": 1784105403.0
  }
]