[
  {
    "title": "東北大学『山上さんありがとう』と書かれてるポスターを貼られてブチギレ",
    "url": "http://blog.livedoor.jp/kinisoku/archives/5691660.html",
    "blog_title": "キニ速",
    "date": "2026-07-12 23:40",
    "timestamp": 1783899610.0
  },
  {
    "title": "【物議】女性VTuber「V好きな人嫌い。男として弱者男性だから」発言で界隈大荒れ",
    "url": "https://alfalfalfa.com/articles/11087080.html",
    "blog_title": "アルファルファモザイク＠ネットニュースのまとめ",
    "date": "2026-07-12 23:30",
    "timestamp": 1783899010.0
  },
  {
    "title": "今月から都民になるけど地下鉄わけわからなすぎる",
    "url": "http://blog.livedoor.jp/goldennews/archives/52304869.html",
    "blog_title": "ゴールデンタイムズ",
    "date": "2026-07-12 23:12",
    "timestamp": 1783897920.0
  },
  {
    "title": "【衝撃】中国・六藍ダム、決壊前後の上空写真がヤバすぎる…",
    "url": "https://nwknews.jp/archives/6249257.html",
    "blog_title": "哲学ニュースnwk",
    "date": "2026-07-12 23:00",
    "timestamp": 1783897215.0
  },
  {
    "title": "【大荒れ】麻生泰氏「Fランの学費出すなら豊胸した方がいい」発言で賛否",
    "url": "https://alfalfalfa.com/articles/11087019.html",
    "blog_title": "アルファルファモザイク＠ネットニュースのまとめ",
    "date": "2026-07-12 23:00",
    "timestamp": 1783897214.0
  },
  {
    "title": "「やっぱりだめだ」富士山下山中に疲労で動けなくなった男性（54）が再び救助要請…登山時に引き続き2日連続で救助求める",
    "url": "https://itainews.com/archives/2064745.html",
    "blog_title": "痛いニュース(ﾉ∀`)",
    "date": "2026-07-12 23:00",
    "timestamp": 1783897212.0
  },
  {
    "title": "【悲報】リュウジさん、名古屋の飯はまずいといい大炎上して謝罪",
    "url": "http://blog.livedoor.jp/kinisoku/archives/5691665.html",
    "blog_title": "キニ速",
    "date": "2026-07-12 23:00",
    "timestamp": 1783897206.0
  },
  {
    "title": "【画像】女さん「映画館のポップコーンだいすき」パシャッ 【Pickup12061052】",
    "url": "https://alfalfalfa.com/articles/11086780.html",
    "blog_title": "アルファルファモザイク＠ネットニュースのまとめ",
    "date": "2026-07-12 22:50",
    "timestamp": 1783896638.0
  },
  {
    "title": "CRTモニターに掲示板の画面を映すだけでエモい",
    "url": "https://hamusoku.com/archives/11014488.html",
    "blog_title": "ハムスター速報",
    "date": "2026-07-12 22:44",
    "timestamp": 1783896240.0
  },
  {
    "title": "【画像】緋村剣心さんに悲しき過去……",
    "url": "http://blog.livedoor.jp/goldennews/archives/52305226.html",
    "blog_title": "ゴールデンタイムズ",
    "date": "2026-07-12 22:39",
    "timestamp": 1783895992.0
  },
  {
    "title": "【画像】Z女子「ちょっと待って！！イオンに謎のキノコ歩いてる！！！」→5いいねｗｗｗ",
    "url": "http://blog.livedoor.jp/kinisoku/archives/5691644.html",
    "blog_title": "キニ速",
    "date": "2026-07-12 22:30",
    "timestamp": 1783895449.0
  },
  {
    "title": "【動画】イエローストーンで観光客がバイソンに接近→警告無視の末に吹っ飛ばされる",
    "url": "https://alfalfalfa.com/articles/11087079.html",
    "blog_title": "アルファルファモザイク＠ネットニュースのまとめ",
    "date": "2026-07-12 22:30",
    "timestamp": 1783895403.0
  },
  {
    "title": "【画像】とあるニュースのポスト、フォントのせいで一部の人達に何かが見えてしまう",
    "url": "http://blog.livedoor.jp/goldennews/archives/52305228.html",
    "blog_title": "ゴールデンタイムズ",
    "date": "2026-07-12 22:12",
    "timestamp": 1783894369.0
  },
  {
    "title": "【疑問】人類は月に行った←冷静に考えて1960年代の技術で本当に可能だったんか？",
    "url": "https://nwknews.jp/archives/6249256.html",
    "blog_title": "哲学ニュースnwk",
    "date": "2026-07-12 22:00",
    "timestamp": 1783893648.0
  },
  {
    "title": "レスバ、クラピカ構文だけで勝てる時代へｗｗｗｗ",
    "url": "http://blog.livedoor.jp/kinisoku/archives/5691611.html",
    "blog_title": "キニ速",
    "date": "2026-07-12 22:00",
    "timestamp": 1783893644.0
  },
  {
    "title": "【動画】トー横キッズ、オッサンを一発KOwwwwwwwww",
    "url": "https://alfalfalfa.com/articles/11087021.html",
    "blog_title": "アルファルファモザイク＠ネットニュースのまとめ",
    "date": "2026-07-12 22:00",
    "timestamp": 1783893640.0
  },
  {
    "title": "【芸能】世良公則「万世一系、天皇の父方を遡ると2600年以上前の初代神武天皇に辿り着く」　皇室典範改正案などをめぐり私見",
    "url": "https://itainews.com/archives/2064734.html",
    "blog_title": "痛いニュース(ﾉ∀`)",
    "date": "2026-07-12 22:00",
    "timestamp": 1783893605.0
  },
  {
    "title": "【北海道】 ジンギスカンのタレ「ベル」VS「ソラチ」とかいう、道民を真っ二つに引き裂く戦争",
    "url": "http://blog.livedoor.jp/goldennews/archives/52305276.html",
    "blog_title": "ゴールデンタイムズ",
    "date": "2026-07-12 21:41",
    "timestamp": 1783892509.0
  },
  {
    "title": "水島努監督「ヤニねこみたいな作品やりたいから仕事ください」",
    "url": "http://blog.livedoor.jp/goldennews/archives/52305275.html",
    "blog_title": "ゴールデンタイムズ",
    "date": "2026-07-12 21:34",
    "timestamp": 1783892061.0
  },
  {
    "title": "【朗報】日本国「学校の体育館のエアコン、『家庭用』にしたら安く済むじゃん！！！」",
    "url": "http://blog.livedoor.jp/kinisoku/archives/5691657.html",
    "blog_title": "キニ速",
    "date": "2026-07-12 21:30",
    "timestamp": 1783891813.0
  },
  {
    "title": "【悲報】女さん、正論言われただけでモラハラ扱いwwwwwww",
    "url": "http://blog.livedoor.jp/news23vip/archives/6249248.html",
    "blog_title": "VIPPERな俺",
    "date": "2026-07-12 21:00",
    "timestamp": 1783890038.0
  },
  {
    "title": "仮面ライダーと戦隊の名作で打線組んだwwwwwwwwy",
    "url": "http://blog.livedoor.jp/news23vip/archives/6249251.html",
    "blog_title": "VIPPERな俺",
    "date": "2026-07-12 18:00",
    "timestamp": 1783879234.0
  },
  {
    "title": "お前らが「これは反則やろｗｗｗ」ってなった爆笑画像貼ってけ",
    "url": "https://nwknews.jp/archives/6249249.html",
    "blog_title": "哲学ニュースnwk",
    "date": "2026-07-12 16:00",
    "timestamp": 1783872029.0
  },
  {
    "title": "お前らがAmazonプライムデーで買った物を教えてください",
    "url": "https://nwknews.jp/archives/6249244.html",
    "blog_title": "哲学ニュースnwk",
    "date": "2026-07-12 15:08",
    "timestamp": 1783868881.0
  },
  {
    "title": "環境活動家「地球が保たん時が来ているのだ。なぜそれがわからない！」←これ異常だよな",
    "url": "http://blog.livedoor.jp/news23vip/archives/6249246.html",
    "blog_title": "VIPPERな俺",
    "date": "2026-07-12 15:01",
    "timestamp": 1783868514.0
  },
  {
    "title": "酒やめたら人生豊かになるんか？",
    "url": "http://blog.livedoor.jp/news23vip/archives/6249243.html",
    "blog_title": "VIPPERな俺",
    "date": "2026-07-12 14:26",
    "timestamp": 1783866381.0
  },
  {
    "title": "パチンコ20円・スロット100円化へ ホール4団体が警察庁に要望書検討",
    "url": "https://itainews.com/archives/2064743.html",
    "blog_title": "痛いニュース(ﾉ∀`)",
    "date": "2026-07-12 14:01",
    "timestamp": 1783864897.0
  },
  {
    "title": "お前らの地元にある「全国でも絶対通用するやろ」ってローカルチェーン教えて",
    "url": "https://nwknews.jp/archives/6249240.html",
    "blog_title": "哲学ニュースnwk",
    "date": "2026-07-12 14:00",
    "timestamp": 1783864816.0
  },
  {
    "title": "中国政府　台湾南方のフィリピン領バタン諸島も中国の領土だと主張開始",
    "url": "https://hamusoku.com/archives/11019972.html",
    "blog_title": "ハムスター速報",
    "date": "2026-07-12 13:30",
    "timestamp": 1783863010.0
  },
  {
    "title": "フランス！イングランド！アルゼンチン！スペイン！",
    "url": "http://blog.livedoor.jp/news23vip/archives/6249238.html",
    "blog_title": "VIPPERな俺",
    "date": "2026-07-12 13:27",
    "timestamp": 1783862822.0
  },
  {
    "title": "アメリカ人男性、フィリピンで傘で叩かれブチ切れ応戦も射殺され死亡",
    "url": "https://itainews.com/archives/2064736.html",
    "blog_title": "痛いニュース(ﾉ∀`)",
    "date": "2026-07-12 13:01",
    "timestamp": 1783861287.0
  },
  {
    "title": "【千葉】1日1000人利用のバス廃止へ　千葉市花見川区　「運転士不足」代替交通なし　住民存続求めるが…",
    "url": "https://itainews.com/archives/2064735.html",
    "blog_title": "痛いニュース(ﾉ∀`)",
    "date": "2026-07-12 12:02",
    "timestamp": 1783857741.0
  },
  {
    "title": "【鴨川シーワールド】シャチさんに「いないいないばあ！」←反応がかわいすぎて１０万いいね",
    "url": "https://hamusoku.com/archives/11020078.html",
    "blog_title": "ハムスター速報",
    "date": "2026-07-12 11:07",
    "timestamp": 1783854455.0
  },
  {
    "title": "JR西日本が『エスカレーター片側空ける謎の文化』に注意喚起",
    "url": "https://hamusoku.com/archives/11020076.html",
    "blog_title": "ハムスター速報",
    "date": "2026-07-12 09:35",
    "timestamp": 1783848911.0
  },
  {
    "title": "【高校野球東東京大会】超高学歴対決　日比谷ｖｓ開成戦のラストが衝撃的すぎると話題に",
    "url": "https://hamusoku.com/archives/11020069.html",
    "blog_title": "ハムスター速報",
    "date": "2026-07-12 08:04",
    "timestamp": 1783843491.0
  }
]