[
  {
    "title": "【悲報】タワレコ、遂に閉店ラッシュwwwwwwwww",
    "url": "http://blog.livedoor.jp/kinisoku/archives/5681709.html",
    "blog_title": "キニ速",
    "date": "2026-05-28 10:40",
    "timestamp": 1779964826.0
  },
  {
    "title": "【速報】 イラン、米軍基地を攻撃",
    "url": "https://itainews.com/archives/2062974.html",
    "blog_title": "痛いニュース(ﾉ∀`)",
    "date": "2026-05-28 10:31",
    "timestamp": 1779964310.0
  },
  {
    "title": "ワイの人生で打線組んだったｗｗｗ",
    "url": "http://blog.livedoor.jp/news23vip/archives/6243875.html",
    "blog_title": "VIPPERな俺",
    "date": "2026-05-28 10:30",
    "timestamp": 1779964254.0
  },
  {
    "title": "【悲報】巨人OB中畑清氏「俺なんて反抗期の娘の尻を謝るまで叩き続けたことがある」",
    "url": "https://alfalfalfa.com/articles/11044783.html",
    "blog_title": "アルファルファモザイク＠ネットニュースのまとめ",
    "date": "2026-05-28 10:25",
    "timestamp": 1779963926.0
  },
  {
    "title": "中畑清「私も娘が泣いて謝るまで叩き続けたッ！」阿部慎之助にスゴい角度でエールｗｗｗｗｗｗｗｗｗryyyy",
    "url": "http://blog.livedoor.jp/kinisoku/archives/5681684.html",
    "blog_title": "キニ速",
    "date": "2026-05-28 10:20",
    "timestamp": 1779963643.0
  },
  {
    "title": "【悲報】 フェラーリの初フル電動モデル「Luce（ルーチェ）」、ダサい",
    "url": "http://blog.livedoor.jp/goldennews/archives/52303254.html",
    "blog_title": "ゴールデンタイムズ",
    "date": "2026-05-28 10:12",
    "timestamp": 1779963120.0
  },
  {
    "title": "【悲報】『あのちゃんねる』放送終了、6月15日が最終回ｗｗｗｗｗｗｗｗ",
    "url": "http://blog.livedoor.jp/kinisoku/archives/5681719.html",
    "blog_title": "キニ速",
    "date": "2026-05-28 10:03",
    "timestamp": 1779962623.0
  },
  {
    "title": "「私まで家宅捜索されたんです！」日本維新の会のウグイス嬢が「給料をピンハネされた」と怒りの告白",
    "url": "https://itainews.com/archives/2062959.html",
    "blog_title": "痛いニュース(ﾉ∀`)",
    "date": "2026-05-28 10:00",
    "timestamp": 1779962424.0
  },
  {
    "title": "【悲報】少女、メン地下アイドルに300万も搾取されてしまう",
    "url": "https://alfalfalfa.com/articles/11044772.html",
    "blog_title": "アルファルファモザイク＠ネットニュースのまとめ",
    "date": "2026-05-28 09:55",
    "timestamp": 1779962130.0
  },
  {
    "title": "【懲戒処分】税務署員がデリヘル勤務とパパ活　　「地下アイドルの推し活資金を捻出したかった」　関東信越国税局",
    "url": "https://itainews.com/archives/2062958.html",
    "blog_title": "痛いニュース(ﾉ∀`)",
    "date": "2026-05-28 09:30",
    "timestamp": 1779960656.0
  },
  {
    "title": "【画像】インドカレー屋メニュー表の後ろの方にいるこいつらｗｗｗｗ",
    "url": "http://blog.livedoor.jp/kinisoku/archives/5681648.html",
    "blog_title": "キニ速",
    "date": "2026-05-28 09:30",
    "timestamp": 1779960644.0
  },
  {
    "title": "みいちゃんと山田さん、250万部突破ｗｗｗｗｗｗｗｗ",
    "url": "http://blog.livedoor.jp/goldennews/archives/52303262.html",
    "blog_title": "ゴールデンタイムズ",
    "date": "2026-05-28 09:12",
    "timestamp": 1779959542.0
  },
  {
    "title": "女性Vtuber「男は自分より頭のいい女性配信者が嫌い/見ないって層が多い」",
    "url": "https://hamusoku.com/archives/11003052.html",
    "blog_title": "ハムスター速報",
    "date": "2026-05-28 09:11",
    "timestamp": 1779959460.0
  },
  {
    "title": "【辺野古転覆】長野県教組執行委員会、文科省に抗議声明　同志社国際高の教育基本法違反判断巡り",
    "url": "https://itainews.com/archives/2062957.html",
    "blog_title": "痛いニュース(ﾉ∀`)",
    "date": "2026-05-28 09:01",
    "timestamp": 1779958890.0
  },
  {
    "title": "【うっかり】佐藤容疑者、パチンコ店で大麻を落とし、受け取りに行って逮捕",
    "url": "https://alfalfalfa.com/articles/11044741.html",
    "blog_title": "アルファルファモザイク＠ネットニュースのまとめ",
    "date": "2026-05-28 09:00",
    "timestamp": 1779958847.0
  },
  {
    "title": "お前らってホテルに早くついてもチェックイン時間まで黙って待ってそうよな",
    "url": "http://blog.livedoor.jp/news23vip/archives/6243872.html",
    "blog_title": "VIPPERな俺",
    "date": "2026-05-28 09:00",
    "timestamp": 1779958825.0
  },
  {
    "title": "【悲報】ラプラス・ダークネスさん、親と兄弟3人の生活費と学費を1人で養っていたｗｗｗｗｗｗｗｗｗｗｗｗｗｗｗｗｗｗ",
    "url": "http://blog.livedoor.jp/kinisoku/archives/5681626.html",
    "blog_title": "キニ速",
    "date": "2026-05-28 09:00",
    "timestamp": 1779958803.0
  },
  {
    "title": "【画像】男子をガン詰めするJKの目、レベチｗｗｗｗｗｗｗｗｗｗｗｗｗｗｗ【Pickup】",
    "url": "https://alfalfalfa.com/articles/11044589.html",
    "blog_title": "アルファルファモザイク＠ネットニュースのまとめ",
    "date": "2026-05-28 08:50",
    "timestamp": 1779958228.0
  },
  {
    "title": "【悲報】はま寿司、迷惑客にレーン上の寿司へ洗剤ドバドバされる動画が拡散…公式「到底容認できない」",
    "url": "https://nwknews.jp/archives/6243887.html",
    "blog_title": "哲学ニュースnwk",
    "date": "2026-05-28 08:46",
    "timestamp": 1779957989.0
  },
  {
    "title": "【動画】はま寿司、また迷惑客。レーン上の寿司に洗剤をぶっかけられてしまう",
    "url": "https://alfalfalfa.com/articles/11044732.html",
    "blog_title": "アルファルファモザイク＠ネットニュースのまとめ",
    "date": "2026-05-28 08:30",
    "timestamp": 1779957053.0
  },
  {
    "title": "【悲報】 バレーボール日本代表の佐藤駿一郎、パチ屋で大麻所持で逮捕",
    "url": "http://blog.livedoor.jp/goldennews/archives/52303268.html",
    "blog_title": "ゴールデンタイムズ",
    "date": "2026-05-28 08:12",
    "timestamp": 1779955952.0
  },
  {
    "title": "【悲報】ホルムズでまったりしてた韓国貨物船、また攻撃される…何もしてないのになぜ",
    "url": "https://itainews.com/archives/2062956.html",
    "blog_title": "痛いニュース(ﾉ∀`)",
    "date": "2026-05-28 08:02",
    "timestamp": 1779955359.0
  },
  {
    "title": "ラストがひどい漫画上げてけ",
    "url": "http://blog.livedoor.jp/news23vip/archives/6243851.html",
    "blog_title": "VIPPERな俺",
    "date": "2026-05-28 07:30",
    "timestamp": 1779953446.0
  },
  {
    "title": "【中古車販売会社社長】ナイジェリアの高度人材　高級車を盗み海外輸出して大儲け　また不起訴か",
    "url": "https://hamusoku.com/archives/11003058.html",
    "blog_title": "ハムスター速報",
    "date": "2026-05-28 07:16",
    "timestamp": 1779952573.0
  },
  {
    "title": "【北海道･大学生集団暴行】 被告の証言に裁判官と検察が呆れる 「滅茶苦茶っすね…」「理解できない」",
    "url": "http://blog.livedoor.jp/goldennews/archives/52303261.html",
    "blog_title": "ゴールデンタイムズ",
    "date": "2026-05-28 07:12",
    "timestamp": 1779952321.0
  },
  {
    "title": "お前ら「ロピア」っていうコスパ良すぎてえげつないスーパー知ってるか？",
    "url": "https://nwknews.jp/archives/6243867.html",
    "blog_title": "哲学ニュースnwk",
    "date": "2026-05-28 06:17",
    "timestamp": 1779949051.0
  },
  {
    "title": "【朗報】 阿部慎之助の監督復帰署名、10万人突破ｗｗｗｗｗｗｗｗｗｗｗｗｗｗｗｗ",
    "url": "http://blog.livedoor.jp/goldennews/archives/52303258.html",
    "blog_title": "ゴールデンタイムズ",
    "date": "2026-05-28 06:12",
    "timestamp": 1779948758.0
  },
  {
    "title": "女みたいに可愛い男ならヤれるよな",
    "url": "http://blog.livedoor.jp/news23vip/archives/6243844.html",
    "blog_title": "VIPPERな俺",
    "date": "2026-05-28 06:00",
    "timestamp": 1779948005.0
  },
  {
    "title": "ちいかわ Chiikawa Baby ぬいぐるみくじ←集金がエグすぎると話題に",
    "url": "https://hamusoku.com/archives/11003047.html",
    "blog_title": "ハムスター速報",
    "date": "2026-05-28 05:45",
    "timestamp": 1779947102.0
  },
  {
    "title": "【悲報】孤独の死亡リスク、高すぎるwwxwwxxxwwwxw",
    "url": "http://blog.livedoor.jp/news23vip/archives/6243848.html",
    "blog_title": "VIPPERな俺",
    "date": "2026-05-28 04:30",
    "timestamp": 1779942606.0
  },
  {
    "title": "ドラクエ12のヒロイン、ヤバすぎ",
    "url": "https://nwknews.jp/archives/6243862.html",
    "blog_title": "哲学ニュースnwk",
    "date": "2026-05-28 04:10",
    "timestamp": 1779941442.0
  },
  {
    "title": "妻「アルファードは残クレ扱いされて乗りたくない！もっと良い車に買い替えたい！！！」←これ",
    "url": "https://hamusoku.com/archives/11002707.html",
    "blog_title": "ハムスター速報",
    "date": "2026-05-28 03:50",
    "timestamp": 1779940202.0
  },
  {
    "title": "【悲報】孤独の死亡リスク、高すぎるｗｗｗｗｗ",
    "url": "https://nwknews.jp/archives/6243859.html",
    "blog_title": "哲学ニュースnwk",
    "date": "2026-05-28 02:36",
    "timestamp": 1779935793.0
  },
  {
    "title": "日本人看護師の賃金が絶対に上がらない現実　中国人看護師が大量に送り込まれる",
    "url": "https://hamusoku.com/archives/11002804.html",
    "blog_title": "ハムスター速報",
    "date": "2026-05-28 02:05",
    "timestamp": 1779933950.0
  },
  {
    "title": "成功する奴ってまじで体力がバケモンだよな",
    "url": "https://nwknews.jp/archives/6243845.html",
    "blog_title": "哲学ニュースnwk",
    "date": "2026-05-28 00:50",
    "timestamp": 1779929435.0
  }
]