[
  {
    "title": "【野球脳】開智未来高校野球部　日大三高野球部による女子高生わいせつ動画拡散を擁護して大炎上　逃亡へ",
    "url": "https://hamusoku.com/archives/10968607.html",
    "blog_title": "ハムスター速報",
    "date": "2026-02-14 22:06",
    "timestamp": 1771106763.0
  },
  {
    "title": "【画像】トム・クルーズの娘(19)が恵体すぎるｗｗｗｗｗｗｗｗ",
    "url": "http://blog.livedoor.jp/kinisoku/archives/5659549.html",
    "blog_title": "キニ速",
    "date": "2026-02-14 22:02",
    "timestamp": 1771106552.0
  },
  {
    "title": "【岡山】30代女性(長髪・赤色長袖・白ｽｶｰﾄ)　男子中学生へ「お金に困るでしょ」「これでお菓子でも買って食べて」…金銭を渡す",
    "url": "https://itainews.com/archives/2058848.html",
    "blog_title": "痛いニュース(ﾉ∀`)",
    "date": "2026-02-14 22:02",
    "timestamp": 1771106545.0
  },
  {
    "title": "【悲報】ゴールドマンサックス経営陣、エプスタインがバレて辞任wwwwwwwwwwwwwwwwwwwwwwwwwww",
    "url": "https://alfalfalfa.com/articles/11009744.html",
    "blog_title": "アルファルファモザイク＠ネットニュースのまとめ",
    "date": "2026-02-14 22:01",
    "timestamp": 1771106518.0
  },
  {
    "title": "【画像】JK「脳洗浄ほんっとにね最高すぎる！顔が短くなって、足がスッキリするの～ｗ」",
    "url": "http://blog.livedoor.jp/kinisoku/archives/5659489.html",
    "blog_title": "キニ速",
    "date": "2026-02-14 21:30",
    "timestamp": 1771104658.0
  },
  {
    "title": "【速報】大阪の通り魔事件、思った以上にヤバすぎる。",
    "url": "https://alfalfalfa.com/articles/11009761.html",
    "blog_title": "アルファルファモザイク＠ネットニュースのまとめ",
    "date": "2026-02-14 21:30",
    "timestamp": 1771104645.0
  },
  {
    "title": "【すげえ】蓮舫、Xのヘッダーを中道から立憲民主党に堂々と戻すwwwwwwwwwwww",
    "url": "https://alfalfalfa.com/articles/11009739.html",
    "blog_title": "アルファルファモザイク＠ネットニュースのまとめ",
    "date": "2026-02-14 21:20",
    "timestamp": 1771104001.0
  },
  {
    "title": "サンド伊達さん、血圧が200を超える 「降圧剤飲んでるから大丈夫」",
    "url": "http://blog.livedoor.jp/goldennews/archives/52298729.html",
    "blog_title": "ゴールデンタイムズ",
    "date": "2026-02-14 21:12",
    "timestamp": 1771103548.0
  },
  {
    "title": "【悲報】Z世代男子、アレのせいで女嫌いが急増中...",
    "url": "http://blog.livedoor.jp/kinisoku/archives/5659257.html",
    "blog_title": "キニ速",
    "date": "2026-02-14 21:00",
    "timestamp": 1771102858.0
  },
  {
    "title": "【悲報】早稲田駅徒歩7分､4畳､キッチンの隣にすぐ便器 これで家賃58000円ｗｗｗｗｗｗｗｗｗｗ",
    "url": "https://alfalfalfa.com/articles/11009723.html",
    "blog_title": "アルファルファモザイク＠ネットニュースのまとめ",
    "date": "2026-02-14 21:00",
    "timestamp": 1771102839.0
  },
  {
    "title": "【悲報】オリンピック、フランス人女性審判がとんでもないライン越えで物議ｗｗｗｗｗｗｗｗｗｗｗｗｗｗｗｗｗｗｗｗｗｗｗ【HotTweets】",
    "url": "https://alfalfalfa.com/articles/11009513.html",
    "blog_title": "アルファルファモザイク＠ネットニュースのまとめ",
    "date": "2026-02-14 20:50",
    "timestamp": 1771102205.0
  },
  {
    "title": "耳掃除、気持ちよすぎるｗｗｗｗｗｗｗｗｗｗｗｗｗｗｗ",
    "url": "http://blog.livedoor.jp/goldennews/archives/52298728.html",
    "blog_title": "ゴールデンタイムズ",
    "date": "2026-02-14 20:12",
    "timestamp": 1771099967.0
  },
  {
    "title": "中道改革連合さん、さっそく消え去ろうとしていたｗｗｗｗ",
    "url": "http://blog.livedoor.jp/kinisoku/archives/5659255.html",
    "blog_title": "キニ速",
    "date": "2026-02-14 20:00",
    "timestamp": 1771099237.0
  },
  {
    "title": "FF2←コイツがガチで不人気な理由",
    "url": "http://blog.livedoor.jp/goldennews/archives/52298727.html",
    "blog_title": "ゴールデンタイムズ",
    "date": "2026-02-14 19:12",
    "timestamp": 1771096340.0
  },
  {
    "title": "【トリッカル】 シオン・ザ・DBさん、不憫すぎて可愛い",
    "url": "http://blog.livedoor.jp/goldennews/archives/52298726.html",
    "blog_title": "ゴールデンタイムズ",
    "date": "2026-02-14 18:12",
    "timestamp": 1771092733.0
  },
  {
    "title": "俺が毎朝通勤で横を通る工場があってさ……",
    "url": "http://blog.livedoor.jp/goldennews/archives/52297948.html",
    "blog_title": "ゴールデンタイムズ",
    "date": "2026-02-14 17:50",
    "timestamp": 1771091400.0
  },
  {
    "title": "【悲報】インフルB、39.4℃になってしまう・・・・・・",
    "url": "http://blog.livedoor.jp/kinisoku/archives/5659429.html",
    "blog_title": "キニ速",
    "date": "2026-02-14 17:02",
    "timestamp": 1771088525.0
  },
  {
    "title": "夜中に見ると危険な画像貼るのだ",
    "url": "https://nwknews.jp/archives/6231901.html",
    "blog_title": "哲学ニュースnwk",
    "date": "2026-02-14 16:23",
    "timestamp": 1771086180.0
  },
  {
    "title": "女子高生わいせつ動画拡散の性犯罪者集団『日大三高野球部』を守る為に日大三高経営陣　動く",
    "url": "https://hamusoku.com/archives/10968604.html",
    "blog_title": "ハムスター速報",
    "date": "2026-02-14 15:01",
    "timestamp": 1771081309.0
  },
  {
    "title": "【朗報】メモリ価格下がり始める。32GB 6.5万円",
    "url": "http://blog.livedoor.jp/news23vip/archives/6231899.html",
    "blog_title": "VIPPERな俺",
    "date": "2026-02-14 14:55",
    "timestamp": 1771080916.0
  },
  {
    "title": "【悲報】Z世代、人類史上はじめて世代レベルで知能が低下していた",
    "url": "https://nwknews.jp/archives/6231891.html",
    "blog_title": "哲学ニュースnwk",
    "date": "2026-02-14 14:20",
    "timestamp": 1771078842.0
  },
  {
    "title": "眉毛整えてるやつってオカマ？",
    "url": "http://blog.livedoor.jp/news23vip/archives/6231890.html",
    "blog_title": "VIPPERな俺",
    "date": "2026-02-14 14:16",
    "timestamp": 1771078616.0
  },
  {
    "title": "【五輪】“日本選手団への中傷投稿” ６・２万件…団長「想定以上の件数、選手の力奪うからやめて」(読売新聞)",
    "url": "https://itainews.com/archives/2058851.html",
    "blog_title": "痛いニュース(ﾉ∀`)",
    "date": "2026-02-14 14:01",
    "timestamp": 1771077660.0
  },
  {
    "title": "高市政権によるビザや永住許可審査の厳格化で成金中国人達がタワマン投げ売り開始",
    "url": "https://hamusoku.com/archives/10968109.html",
    "blog_title": "ハムスター速報",
    "date": "2026-02-14 13:46",
    "timestamp": 1771076787.0
  },
  {
    "title": "ガチでヤバかったコピペ貼ってけ・・・",
    "url": "https://nwknews.jp/archives/6231886.html",
    "blog_title": "哲学ニュースnwk",
    "date": "2026-02-14 13:31",
    "timestamp": 1771075903.0
  },
  {
    "title": "中国が台湾を武力統一なら｢次は日本｣　台湾・頼総統の発言、総統府が発表",
    "url": "https://itainews.com/archives/2058845.html",
    "blog_title": "痛いニュース(ﾉ∀`)",
    "date": "2026-02-14 13:02",
    "timestamp": 1771074135.0
  },
  {
    "title": "(ヽ´ん`)「不審者がいるから気を付けて、俺が不審者や」 女子中学生に声がけ 小柄で灰色スウェットの男",
    "url": "https://itainews.com/archives/2058844.html",
    "blog_title": "痛いニュース(ﾉ∀`)",
    "date": "2026-02-14 12:02",
    "timestamp": 1771070576.0
  },
  {
    "title": "【悲報】ゴールドマンサックス経営陣、エプスタインがバレて辞任wwwwwwww",
    "url": "https://nwknews.jp/archives/6231874.html",
    "blog_title": "哲学ニュースnwk",
    "date": "2026-02-14 11:48",
    "timestamp": 1771069724.0
  },
  {
    "title": "東京新聞「#ママ戦争止めてくるわ」",
    "url": "https://itainews.com/archives/2058856.html",
    "blog_title": "痛いニュース(ﾉ∀`)",
    "date": "2026-02-14 11:31",
    "timestamp": 1771068714.0
  },
  {
    "title": "小学校・中学校の今思うと理不尽なルール",
    "url": "https://hamusoku.com/archives/10968510.html",
    "blog_title": "ハムスター速報",
    "date": "2026-02-14 11:21",
    "timestamp": 1771068076.0
  },
  {
    "title": "【動画】ロボットアニメの名曲といえば",
    "url": "http://blog.livedoor.jp/news23vip/archives/6231865.html",
    "blog_title": "VIPPERな俺",
    "date": "2026-02-14 10:33",
    "timestamp": 1771065201.0
  },
  {
    "title": "【悲報】大食いしまくったフードファイターの後遺症、ついに明かされ始めるwwwwww",
    "url": "https://nwknews.jp/archives/6231857.html",
    "blog_title": "哲学ニュースnwk",
    "date": "2026-02-14 09:40",
    "timestamp": 1771062042.0
  },
  {
    "title": "【日大三高】女子高生のわいせつ動画を拡散した野球部の犯罪者達　なぜか退学もせずに活動休止の甘々処分で終わる",
    "url": "https://hamusoku.com/archives/10968563.html",
    "blog_title": "ハムスター速報",
    "date": "2026-02-14 09:37",
    "timestamp": 1771061829.0
  },
  {
    "title": "最強の袋ラーメン決めようや",
    "url": "http://blog.livedoor.jp/news23vip/archives/6231840.html",
    "blog_title": "VIPPERな俺",
    "date": "2026-02-14 09:00",
    "timestamp": 1771059611.0
  },
  {
    "title": "お前ら正直彼女いたことある？",
    "url": "http://blog.livedoor.jp/news23vip/archives/6231839.html",
    "blog_title": "VIPPERな俺",
    "date": "2026-02-14 07:30",
    "timestamp": 1771054228.0
  }
]