[
  {
    "title": "TBSサンモニ、文科省の教育基本法違反認定にお怒りの様子😡",
    "url": "https://alfalfalfa.com/articles/11043350.html",
    "blog_title": "アルファルファモザイク＠ネットニュースのまとめ",
    "date": "2026-05-24 06:03",
    "timestamp": 1779602590.0
  },
  {
    "title": "【宮崎】鶏の刺身や地鶏のタタキを食べたか…飲食店で集団食中毒、カンピロバクター属菌を検出",
    "url": "https://itainews.com/archives/2062799.html",
    "blog_title": "痛いニュース(ﾉ∀`)",
    "date": "2026-05-24 06:01",
    "timestamp": 1779602516.0
  },
  {
    "title": "初ガツオにはDHAが少なく戻りガツオにはDHAが多い事実",
    "url": "http://blog.livedoor.jp/news23vip/archives/6243393.html",
    "blog_title": "VIPPERな俺",
    "date": "2026-05-24 06:01",
    "timestamp": 1779602512.0
  },
  {
    "title": "【大朗報】低身長男子、遺伝子的に顔整い(美形)が多いことが証明される　低身長の時代が来るw",
    "url": "http://blog.livedoor.jp/kinisoku/archives/5680671.html",
    "blog_title": "キニ速",
    "date": "2026-05-24 05:44",
    "timestamp": 1779601464.0
  },
  {
    "title": "【洒落怖】洒落にならない怖い話『知らない公園』",
    "url": "https://nwknews.jp/archives/6243391.html",
    "blog_title": "哲学ニュースnwk",
    "date": "2026-05-24 05:42",
    "timestamp": 1779601342.0
  },
  {
    "title": "ひろゆき、高市を論破「『原油は足りてる』と言うと嘘になるので『足りてるという認識』と言ってるw」",
    "url": "https://itainews.com/archives/2062796.html",
    "blog_title": "痛いニュース(ﾉ∀`)",
    "date": "2026-05-24 05:31",
    "timestamp": 1779600681.0
  },
  {
    "title": "【闇深】あのちゃん、テレ朝番組に限界「もう続けたくない」→ “嫌な企画やめて”訴えるも改善されず降板へ…",
    "url": "https://alfalfalfa.com/articles/11043272.html",
    "blog_title": "アルファルファモザイク＠ネットニュースのまとめ",
    "date": "2026-05-24 05:30",
    "timestamp": 1779600659.0
  },
  {
    "title": "【悲報】わい、理不尽すぎる理由でメルカリから168時間BANを食らう",
    "url": "http://blog.livedoor.jp/kinisoku/archives/5680657.html",
    "blog_title": "キニ速",
    "date": "2026-05-24 05:13",
    "timestamp": 1779599580.0
  },
  {
    "title": "新人が仕事を覚えてくれなくて困ってるんやが…",
    "url": "https://hamusoku.com/archives/10996509.html",
    "blog_title": "ハムスター速報",
    "date": "2026-05-24 05:08",
    "timestamp": 1779599327.0
  },
  {
    "title": "【悲報】海外投資ファンド「KADOKAWAは今すぐ夏野剛をクビにしろ」→ 株主からガチで詰められてしまう",
    "url": "https://alfalfalfa.com/articles/11043241.html",
    "blog_title": "アルファルファモザイク＠ネットニュースのまとめ",
    "date": "2026-05-24 05:00",
    "timestamp": 1779598840.0
  },
  {
    "title": "【速報】中国の炭鉱で爆発　５０人以上死亡",
    "url": "https://itainews.com/archives/2062794.html",
    "blog_title": "痛いニュース(ﾉ∀`)",
    "date": "2026-05-24 05:00",
    "timestamp": 1779598803.0
  },
  {
    "title": "【画像】こんな転校生が入ってきたらｗｗｗｗｗｗｗｗｗｗｗｗｗｗｗｗｗｗ【Pickup】",
    "url": "https://alfalfalfa.com/articles/11043221.html",
    "blog_title": "アルファルファモザイク＠ネットニュースのまとめ",
    "date": "2026-05-24 04:50",
    "timestamp": 1779598250.0
  },
  {
    "title": "栃木強盗殺人　事件の数時間前にコンビニ店で手順など確認か",
    "url": "https://itainews.com/archives/2062792.html",
    "blog_title": "痛いニュース(ﾉ∀`)",
    "date": "2026-05-24 04:31",
    "timestamp": 1779597097.0
  },
  {
    "title": "【悲報】あのちゃんが消えて一番“得しそうなタレント”、ガチでこの人説ｗｗｗｗｗ",
    "url": "https://alfalfalfa.com/articles/11043269.html",
    "blog_title": "アルファルファモザイク＠ネットニュースのまとめ",
    "date": "2026-05-24 04:30",
    "timestamp": 1779597026.0
  },
  {
    "title": "リュウジ「食用菊ばら撒くよりオニギリにした方が良いよ♥」→ホリエモン発狂へ😭",
    "url": "http://blog.livedoor.jp/kinisoku/archives/5680654.html",
    "blog_title": "キニ速",
    "date": "2026-05-24 04:27",
    "timestamp": 1779596868.0
  },
  {
    "title": "【大学生集団暴行死】6人全員が死刑もしくは無期懲役の『強盗致死罪』で起訴　奪った金でラーメン…男女3人の裁判員裁判　5月25日初公判",
    "url": "https://itainews.com/archives/2062790.html",
    "blog_title": "痛いニュース(ﾉ∀`)",
    "date": "2026-05-24 04:00",
    "timestamp": 1779595204.0
  },
  {
    "title": "【動画】女子ボートレーサー、勝利者インタビューでとんでもない放送事故をやらかす",
    "url": "http://blog.livedoor.jp/kinisoku/archives/5680635.html",
    "blog_title": "キニ速",
    "date": "2026-05-24 03:49",
    "timestamp": 1779594559.0
  },
  {
    "title": "【2026】NISA人気ランキング、米株はAI祭り、日本株は防衛祭りで草ｗｗｗｗｗ",
    "url": "https://nwknews.jp/archives/6243382.html",
    "blog_title": "哲学ニュースnwk",
    "date": "2026-05-24 03:40",
    "timestamp": 1779594003.0
  },
  {
    "title": "スト6始めたんだけど何からすればいいんだろ",
    "url": "http://blog.livedoor.jp/goldennews/archives/52302886.html",
    "blog_title": "ゴールデンタイムズ",
    "date": "2026-05-24 03:39",
    "timestamp": 1779593940.0
  },
  {
    "title": "【JICA】税金で支援してきたバングラデシュのIT人材　働く場所が無くて無職に　人手不足とはなんだったのか？",
    "url": "https://hamusoku.com/archives/10996840.html",
    "blog_title": "ハムスター速報",
    "date": "2026-05-24 03:38",
    "timestamp": 1779593894.0
  },
  {
    "title": "井手上漠くん、謎の市議に絡まれXでレスバ開始",
    "url": "http://blog.livedoor.jp/kinisoku/archives/5680642.html",
    "blog_title": "キニ速",
    "date": "2026-05-24 03:25",
    "timestamp": 1779593126.0
  },
  {
    "title": "スライサーやおろし器って怖いよね",
    "url": "http://blog.livedoor.jp/goldennews/archives/52303031.html",
    "blog_title": "ゴールデンタイムズ",
    "date": "2026-05-24 03:12",
    "timestamp": 1779592320.0
  },
  {
    "title": "元セガの名越、完全に行方不明になる",
    "url": "http://blog.livedoor.jp/news23vip/archives/6243371.html",
    "blog_title": "VIPPERな俺",
    "date": "2026-05-24 02:40",
    "timestamp": 1779590450.0
  },
  {
    "title": "【悲報】日本円さん、あのトルコリラより弱い扱いを受けてしまう…",
    "url": "https://nwknews.jp/archives/6243373.html",
    "blog_title": "哲学ニュースnwk",
    "date": "2026-05-24 02:38",
    "timestamp": 1779590297.0
  },
  {
    "title": "なんかゲームの公的なアーカイブ機関みたいなの作った方がいいんじゃないか？",
    "url": "http://blog.livedoor.jp/goldennews/archives/52300065.html",
    "blog_title": "ゴールデンタイムズ",
    "date": "2026-05-24 02:12",
    "timestamp": 1779588720.0
  },
  {
    "title": "高齢者が賃貸で家を借りられない問題←NPOさん　利権チューチューの匂いを嗅ぎつけ動き出す",
    "url": "https://hamusoku.com/archives/10996834.html",
    "blog_title": "ハムスター速報",
    "date": "2026-05-24 02:08",
    "timestamp": 1779588532.0
  },
  {
    "title": "あのちゃん「鈴木紗理奈嫌いw」→「番組辞めます」",
    "url": "http://blog.livedoor.jp/news23vip/archives/6243364.html",
    "blog_title": "VIPPERな俺",
    "date": "2026-05-24 01:43",
    "timestamp": 1779587030.0
  },
  {
    "title": "【洒落怖】洒落にならない怖い話『見たくない』",
    "url": "https://nwknews.jp/archives/6243362.html",
    "blog_title": "哲学ニュースnwk",
    "date": "2026-05-24 01:30",
    "timestamp": 1779586201.0
  },
  {
    "title": "コンテナ密輸の手口が巧妙化…ランクルもバラバラにして運ばれる",
    "url": "http://blog.livedoor.jp/goldennews/archives/52302981.html",
    "blog_title": "ゴールデンタイムズ",
    "date": "2026-05-24 01:12",
    "timestamp": 1779585120.0
  },
  {
    "title": "AIイラストが市民権得られない理由",
    "url": "http://blog.livedoor.jp/news23vip/archives/6243357.html",
    "blog_title": "VIPPERな俺",
    "date": "2026-05-24 01:11",
    "timestamp": 1779585097.0
  },
  {
    "title": "日本人は子供を作らない。なぜなら養えないからだ。外国人は子供を作る。なぜなら日本人が養ってくれるからだ。",
    "url": "https://hamusoku.com/archives/10997000.html",
    "blog_title": "ハムスター速報",
    "date": "2026-05-24 01:09",
    "timestamp": 1779584990.0
  },
  {
    "title": "こいつはアオバト　謎多きハトだ",
    "url": "http://blog.livedoor.jp/goldennews/archives/52303016.html",
    "blog_title": "ゴールデンタイムズ",
    "date": "2026-05-24 00:12",
    "timestamp": 1779581520.0
  },
  {
    "title": "【沖縄】玉城デニー知事「踏み込みすぎだ」　文科省が同志社国際高の学習プログラムを“政治的中立に反する”と判断したことに苦言",
    "url": "https://nwknews.jp/archives/6243351.html",
    "blog_title": "哲学ニュースnwk",
    "date": "2026-05-23 23:41",
    "timestamp": 1779579700.0
  },
  {
    "title": "女性「早く結婚したい」ワイ(←)",
    "url": "https://hamusoku.com/archives/10994381.html",
    "blog_title": "ハムスター速報",
    "date": "2026-05-23 22:34",
    "timestamp": 1779575640.0
  },
  {
    "title": "ホッピーとかいう謎すぎる酒",
    "url": "http://blog.livedoor.jp/news23vip/archives/6243278.html",
    "blog_title": "VIPPERな俺",
    "date": "2026-05-23 10:30",
    "timestamp": 1779532206.0
  }
]