[
  {
    "title": "大手Vtuber事務所、ジャニーズのグッズをパクリ大炎上",
    "url": "http://blog.livedoor.jp/kinisoku/archives/5686211.html",
    "blog_title": "キニ速",
    "date": "2026-06-18 11:40",
    "timestamp": 1781782804.0
  },
  {
    "title": "『ヒトナー』、図書館司書のゴ・リラ・リラさんが登場",
    "url": "http://blog.livedoor.jp/goldennews/archives/52304210.html",
    "blog_title": "ゴールデンタイムズ",
    "date": "2026-06-18 11:39",
    "timestamp": 1781782780.0
  },
  {
    "title": "中国人を不正入国させていた会社役員の男とその妻を逮捕",
    "url": "https://itainews.com/archives/2063782.html",
    "blog_title": "痛いニュース(ﾉ∀`)",
    "date": "2026-06-18 11:31",
    "timestamp": 1781782314.0
  },
  {
    "title": "カーチャン「東京に住む息子に食品送ったろ！！！」",
    "url": "https://hamusoku.com/archives/11012968.html",
    "blog_title": "ハムスター速報",
    "date": "2026-06-18 11:30",
    "timestamp": 1781782200.0
  },
  {
    "title": "【悲報】ワイ、逮捕されるｗｗｗｗｗｗｗｗｗｗｗｗｗ",
    "url": "http://blog.livedoor.jp/kinisoku/archives/5686172.html",
    "blog_title": "キニ速",
    "date": "2026-06-18 11:20",
    "timestamp": 1781781613.0
  },
  {
    "title": "【画像】永野芽郁、暇になってビジュ激変",
    "url": "https://alfalfalfa.com/articles/11052027.html",
    "blog_title": "アルファルファモザイク＠ネットニュースのまとめ",
    "date": "2026-06-18 11:15",
    "timestamp": 1781781325.0
  },
  {
    "title": "「登山道で刃物で刺された」と通報した男、自作自演と判明「保険金目当てで自殺しようとしたけど痛かったので119番した」",
    "url": "http://blog.livedoor.jp/goldennews/archives/52304207.html",
    "blog_title": "ゴールデンタイムズ",
    "date": "2026-06-18 11:12",
    "timestamp": 1781781175.0
  },
  {
    "title": "ミャンマー「日本は軍国主義をやめなさい！！」",
    "url": "https://itainews.com/archives/2063769.html",
    "blog_title": "痛いニュース(ﾉ∀`)",
    "date": "2026-06-18 11:01",
    "timestamp": 1781780477.0
  },
  {
    "title": "【画像】角煮を作りますやで！",
    "url": "http://blog.livedoor.jp/news23vip/archives/6246288.html",
    "blog_title": "VIPPERな俺",
    "date": "2026-06-18 11:00",
    "timestamp": 1781780451.0
  },
  {
    "title": "【悲報】有名コスプレイヤーのオフパコ流出、なぜか話題にならない",
    "url": "http://blog.livedoor.jp/kinisoku/archives/5686192.html",
    "blog_title": "キニ速",
    "date": "2026-06-18 11:00",
    "timestamp": 1781780438.0
  },
  {
    "title": "女性「女に生まれただけで、何人のアインシュタインが皿洗いをして一生を終えてるのか」",
    "url": "https://nwknews.jp/archives/6246274.html",
    "blog_title": "哲学ニュースnwk",
    "date": "2026-06-18 11:00",
    "timestamp": 1781780404.0
  },
  {
    "title": "【動画】モスクワ、燃ゆ",
    "url": "https://alfalfalfa.com/articles/11052019.html",
    "blog_title": "アルファルファモザイク＠ネットニュースのまとめ",
    "date": "2026-06-18 10:40",
    "timestamp": 1781779242.0
  },
  {
    "title": "【悲報】サウジアラビア人「俺らの代表がロッカールーム掃除しても誰も興味を持ってくれない。日本じゃないから」",
    "url": "http://blog.livedoor.jp/kinisoku/archives/5686161.html",
    "blog_title": "キニ速",
    "date": "2026-06-18 10:40",
    "timestamp": 1781779218.0
  },
  {
    "title": "『ニセモノの錬金術師』、TVアニメ化ｗｗｗｗｗｗｗｗｗ",
    "url": "http://blog.livedoor.jp/goldennews/archives/52304211.html",
    "blog_title": "ゴールデンタイムズ",
    "date": "2026-06-18 10:39",
    "timestamp": 1781779161.0
  },
  {
    "title": "女さん「女に生まれただけで、何人のアインシュタインが皿洗いをして一生を終えてるのか」",
    "url": "https://itainews.com/archives/2063775.html",
    "blog_title": "痛いニュース(ﾉ∀`)",
    "date": "2026-06-18 10:31",
    "timestamp": 1781778669.0
  },
  {
    "title": "彡(^)(^)「見て見て片腕が無いの」",
    "url": "http://blog.livedoor.jp/kinisoku/archives/5686183.html",
    "blog_title": "キニ速",
    "date": "2026-06-18 10:20",
    "timestamp": 1781778021.0
  },
  {
    "title": "『ぼっち・ざ・ろっく!』の幻の初期山田、復活する",
    "url": "http://blog.livedoor.jp/goldennews/archives/52304205.html",
    "blog_title": "ゴールデンタイムズ",
    "date": "2026-06-18 10:12",
    "timestamp": 1781777547.0
  },
  {
    "title": "【画像】橋本環奈と中川大志の表参道デート、オーラが凄すぎて即バレwwwwwwwww",
    "url": "https://alfalfalfa.com/articles/11052011.html",
    "blog_title": "アルファルファモザイク＠ネットニュースのまとめ",
    "date": "2026-06-18 10:11",
    "timestamp": 1781777481.0
  },
  {
    "title": "【広島】すれちがいざまに面識ない女性（31）の腹を殴ったか　国交省中国運輸局に勤務する男（45）を暴行容疑で逮捕",
    "url": "https://itainews.com/archives/2063768.html",
    "blog_title": "痛いニュース(ﾉ∀`)",
    "date": "2026-06-18 10:03",
    "timestamp": 1781777030.0
  },
  {
    "title": "DAZN、日本の乞食に絶望",
    "url": "http://blog.livedoor.jp/news23vip/archives/6246283.html",
    "blog_title": "VIPPERな俺",
    "date": "2026-06-18 10:03",
    "timestamp": 1781777023.0
  },
  {
    "title": "【ロシア負けそう】ロシアの首都モスクワ　ウクライナによってボコボコに破壊される",
    "url": "https://hamusoku.com/archives/11012998.html",
    "blog_title": "ハムスター速報",
    "date": "2026-06-18 10:02",
    "timestamp": 1781776941.0
  },
  {
    "title": "【朗報】イラン、一人勝ちしてしまう……",
    "url": "http://blog.livedoor.jp/news23vip/archives/6246279.html",
    "blog_title": "VIPPERな俺",
    "date": "2026-06-18 09:37",
    "timestamp": 1781775443.0
  },
  {
    "title": "【悲報】「豆なしコーヒー」飲料、コカ・コーラグループ参入ｗｗｗｗｗｗｗ",
    "url": "https://alfalfalfa.com/articles/11051980.html",
    "blog_title": "アルファルファモザイク＠ネットニュースのまとめ",
    "date": "2026-06-18 09:30",
    "timestamp": 1781775041.0
  },
  {
    "title": "【画像】宇垣美里のJS、JC美少女時代wwwwwww【Pickup18060015】",
    "url": "https://alfalfalfa.com/articles/11051794.html",
    "blog_title": "アルファルファモザイク＠ネットニュースのまとめ",
    "date": "2026-06-18 09:20",
    "timestamp": 1781774418.0
  },
  {
    "title": "【悲報】 歌舞伎町のネズミ、人の脚をいきなり噛んでくる",
    "url": "http://blog.livedoor.jp/goldennews/archives/52304199.html",
    "blog_title": "ゴールデンタイムズ",
    "date": "2026-06-18 09:12",
    "timestamp": 1781773935.0
  },
  {
    "title": "【画像】地方局女子アナ、Xフォロワー数2万人突破",
    "url": "http://blog.livedoor.jp/news23vip/archives/6246275.html",
    "blog_title": "VIPPERな俺",
    "date": "2026-06-18 09:07",
    "timestamp": 1781773625.0
  },
  {
    "title": "「赤ちゃんを飛行機へ連れてくるのはやめて」約60％の人が「機内で子どもに快適さを損なわれた」と回答。周囲への気遣いをめぐり議論に",
    "url": "https://itainews.com/archives/2063767.html",
    "blog_title": "痛いニュース(ﾉ∀`)",
    "date": "2026-06-18 09:02",
    "timestamp": 1781773368.0
  },
  {
    "title": "村上春樹を冷笑しておけば通ぶれる風潮",
    "url": "https://nwknews.jp/archives/6246265.html",
    "blog_title": "哲学ニュースnwk",
    "date": "2026-06-18 09:00",
    "timestamp": 1781773229.0
  },
  {
    "title": "中道・立憲・公明党　週刊文春のＡＩ捏造記事を見ながら合同勉強会を開催ｗｗｗｗｗｗｗｗｗｗｗｗ",
    "url": "https://hamusoku.com/archives/11012972.html",
    "blog_title": "ハムスター速報",
    "date": "2026-06-18 08:10",
    "timestamp": 1781770244.0
  },
  {
    "title": "【激痛】俺が人生で経験した中で最強の「痛み」、痛風なんだけど…お前らの最強痛み体験って何？",
    "url": "https://nwknews.jp/archives/6246263.html",
    "blog_title": "哲学ニュースnwk",
    "date": "2026-06-18 07:00",
    "timestamp": 1781766015.0
  },
  {
    "title": "【大阪】グリ下の薬屋さん　生活保護で２万錠の向精神薬などの薬を無料で手に入れ転売して稼ぎまくる",
    "url": "https://hamusoku.com/archives/11012976.html",
    "blog_title": "ハムスター速報",
    "date": "2026-06-18 06:50",
    "timestamp": 1781765444.0
  },
  {
    "title": "【タブー議論】正直、“男女平等”がここまで社会を変えるとは誰も予想してなかったよな…少子化、結婚離れ、家庭観の崩壊まで全部つながってるのか？",
    "url": "https://nwknews.jp/archives/6246260.html",
    "blog_title": "哲学ニュースnwk",
    "date": "2026-06-18 05:00",
    "timestamp": 1781758818.0
  },
  {
    "title": "EU議会　不法滞在移民の強制送還を厳格化する法案を可決 「あの犯罪者のクソ移民共を送り返せ」議員達がチャント",
    "url": "https://hamusoku.com/archives/11012966.html",
    "blog_title": "ハムスター速報",
    "date": "2026-06-18 04:57",
    "timestamp": 1781758677.0
  },
  {
    "title": "【悲報】セルフレジ、やっぱりあかんかった",
    "url": "http://blog.livedoor.jp/news23vip/archives/6246262.html",
    "blog_title": "VIPPERな俺",
    "date": "2026-06-18 04:34",
    "timestamp": 1781757270.0
  },
  {
    "title": "信用できる人、裏切る人の特徴ってなに？お前らの見分け方教えて",
    "url": "https://nwknews.jp/archives/6246255.html",
    "blog_title": "哲学ニュースnwk",
    "date": "2026-06-18 03:00",
    "timestamp": 1781751613.0
  }
]